.appveyor.yml
.bumpversion.cfg
.cookiecutterrc
.coveragerc
.editorconfig
.travis.yml
AUTHORS.rst
CHANGELOG.rst
CONTRIBUTING.rst
LICENSE
MANIFEST.in
README.rst
requirements.txt
setup.cfg
setup.py
tox.ini
ci/appveyor-bootstrap.py
ci/appveyor-download.py
ci/appveyor-with-compiler.cmd
ci/bootstrap.py
ci/requirements.txt
ci/templates/.appveyor.yml
ci/templates/.travis.yml
ci/templates/appveyor.yml
docs/authors.rst
docs/changelog.rst
docs/conf.py
docs/contributing.rst
docs/index.rst
docs/installation.rst
docs/readme.rst
docs/requirements.txt
docs/spelling_wordlist.txt
docs/usage.rst
docs/reference/edoc_assinatura.rst
docs/reference/index.rst
src/erpbrasil/__init__.py
src/erpbrasil.assinatura.egg-info/PKG-INFO
src/erpbrasil.assinatura.egg-info/SOURCES.txt
src/erpbrasil.assinatura.egg-info/dependency_links.txt
src/erpbrasil.assinatura.egg-info/entry_points.txt
src/erpbrasil.assinatura.egg-info/namespace_packages.txt
src/erpbrasil.assinatura.egg-info/not-zip-safe
src/erpbrasil.assinatura.egg-info/requires.txt
src/erpbrasil.assinatura.egg-info/top_level.txt
src/erpbrasil.assinatura_light.egg-info/PKG-INFO
src/erpbrasil.assinatura_light.egg-info/SOURCES.txt
src/erpbrasil.assinatura_light.egg-info/dependency_links.txt
src/erpbrasil.assinatura_light.egg-info/entry_points.txt
src/erpbrasil.assinatura_light.egg-info/namespace_packages.txt
src/erpbrasil.assinatura_light.egg-info/not-zip-safe
src/erpbrasil.assinatura_light.egg-info/requires.txt
src/erpbrasil.assinatura_light.egg-info/top_level.txt
src/erpbrasil/assinatura/__init__.py
src/erpbrasil/assinatura/__main__.py
src/erpbrasil/assinatura/assinatura.py
src/erpbrasil/assinatura/certificado.py
src/erpbrasil/assinatura/cli.py
src/erpbrasil/assinatura/excecoes.py
src/erpbrasil/assinatura/misc.py
tests/test_erpbrasil_assinatura_pdf.py
tests/test_erpbrasil_assinatura_string.py
tests/test_erpbrasil_assinatura_xml.py
tests/test_erpbrasil_certificado.py
tests/test_erpbrasil_fake_certificate.py
tests/teste.pfx
tests/files/google.pdf
tests/files/nfe-400.xml
tests/fixtures/dummy_cert.pfx
tests/xml/nfe-400-assinado.xml