Metadata-Version: 1.2
Name: erpbrasil.assinatura-nopyopenssl
Version: 1.4.1
Summary: Assinatura de documentos com certificados digitais A1 e A3
Home-page: https://github.com/akretion/erpbrasil.assinatura
Author: Luis Felipe Mileo, Renato Lima
Author-email: raphael.valyi@akretion.com.br
License: MIT license
Project-URL: Documentation, https://erpbrasilassinatura.readthedocs.io/en/latest/
Project-URL: Changelog, https://erpbrasilassinatura.readthedocs.io/en/latest/changelog.html
Project-URL: Issue Tracker, https://github.com/erpbrasil/erpbrasil.assinatura/issues
Platform: UNKNOWN
Classifier: Development Status :: 5 - Production/Stable
Classifier: Intended Audience :: Developers
Classifier: License :: OSI Approved :: MIT License
Classifier: Operating System :: Unix
Classifier: Operating System :: POSIX
Classifier: Operating System :: Microsoft :: Windows
Classifier: Programming Language :: Python
Classifier: Programming Language :: Python :: 3
Classifier: Programming Language :: Python :: 3.5
Classifier: Programming Language :: Python :: 3.6
Classifier: Programming Language :: Python :: 3.7
Classifier: Programming Language :: Python :: Implementation :: CPython
Classifier: Programming Language :: Python :: Implementation :: PyPy
Classifier: Topic :: Utilities
Requires-Python: >=3.5, !=3.0.*, !=3.1.*, !=3.2.*, !=3.3.*
